{
    "first_name": "Chrystal",
    "last_name": "Paulos",
    "emory_email": "cpaulos@emory.edu",
    "title": "Principle Investigator",
    "school": "Emory University",
    "department": "Not explicitly mentioned, but related to the Winship Cancer Institute or Immunology",
    "research_focus": [
        "Human Health"
    ],
    "research_focus_description": "Dr. Chrystal Paulos's research focuses on improving TCR- and CAR-based T cell therapy for cancer immunotherapy, understanding T cell development, and maintaining immunological memory for combating solid tumors.",
    "link_to_bio": []
}